left_pad.py
test_deploy_left_pad-0.0.1.dist-info/LICENSE.txt
test_deploy_left_pad-0.0.1.dist-info/METADATA
test_deploy_left_pad-0.0.1.dist-info/WHEEL
test_deploy_left_pad-0.0.1.dist-info/top_level.txt
test_deploy_left_pad-0.0.1.dist-info/RECORD
